payment_optimizer/__init__.py
payment_optimizer/api/__init__.py
payment_optimizer/api/auth_required.py
payment_optimizer/api/endpoints.py
payment_optimizer/api/granted_user_required.py
payment_optimizer/api/schemas.py
payment_optimizer/api/utils.py
payment_optimizer/db/__init__.py
payment_optimizer/db/basic_etl.py
payment_optimizer/db/csv_files_creator.py
payment_optimizer/db/data_generator.py
payment_optimizer/db/logger.py
payment_optimizer/db/schema.py
payment_optimizer/db/sql_interactions.py
payment_optimizer/modeling/__init__.py
payment_optimizer/modeling/models.py
PayOpt-1.0.2.dist-info/LICENSE
PayOpt-1.0.2.dist-info/METADATA
PayOpt-1.0.2.dist-info/WHEEL
PayOpt-1.0.2.dist-info/top_level.txt
PayOpt-1.0.2.dist-info/RECORD
